sapiclient/__init__.py
sapiclient/s_cache.py
sapiclient/s_cleanup.py
sapiclient/s_config.py
sapiclient/s_db.py
sapiclient/s_log.py
sapiclient/s_net.py
sapiclient/s_util.py
sapiclient/sapiclient.py
sapiclient-0.3.3156.dist-info/WHEEL
sapiclient-0.3.3156.dist-info/METADATA
sapiclient-0.3.3156.dist-info/RECORD
