Metadata-Version: 2.1
Name: sapiclient
Version: 0.3.3156
Summary: 
Author: Zafar Iqbal
Author-email: zaf@sparc.space
Requires-Python: >=3.8,<3.11
Classifier: Programming Language :: Python :: 3
Classifier: Programming Language :: Python :: 3.10
Classifier: Programming Language :: Python :: 3.8
Classifier: Programming Language :: Python :: 3.9
Requires-Dist: requests (>=2.26.0,<3.0.0)
